cipher_wire/__init__.py
cipher_wire/__main__.py
cipher_wire/aes.py
cipher_wire/caeser_cipher.py
cipher_wire/gui.py
cipher_wire/playfair.py
cipher_wire/transpostion_matrix.py
cipher_wire/tests/test_caeser_cipher.py
cipher_wire-0.0.4.dist-info/LICENSE
cipher_wire-0.0.4.dist-info/METADATA
cipher_wire-0.0.4.dist-info/WHEEL
cipher_wire-0.0.4.dist-info/entry_points.txt
cipher_wire-0.0.4.dist-info/top_level.txt
cipher_wire-0.0.4.dist-info/RECORD
